commonroad_global_planner/__init__.py
commonroad_global_planner/global_planner.py
commonroad_global_planner/utils/__init__.py
commonroad_global_planner/utils/smoothing.py
commonroad_global_planner/utils/visualization.py
commonroad_global_planner-0.0.1.dist-info/LICENSE
commonroad_global_planner-0.0.1.dist-info/METADATA
commonroad_global_planner-0.0.1.dist-info/WHEEL
commonroad_global_planner-0.0.1.dist-info/RECORD
